nlcor/__init__.py
nlcor/correlations.py
nlcor/utilities.py
nlcor/visualization.py
nlcor-3.0.3.dist-info/LICENSE
nlcor-3.0.3.dist-info/METADATA
nlcor-3.0.3.dist-info/WHEEL
nlcor-3.0.3.dist-info/top_level.txt
nlcor-3.0.3.dist-info/RECORD
