Metadata-Version: 2.1
Name: nlcor
Version: 3.0.3
Summary: Nlcor uses a dynamic partitioning approach with adaptive segmentation for a more precise nonlinear correlation estimation.
Home-page: https://github.com/ProcessMiner/nlcorpython
Author: Chitta Ranjan, Devleena Banerjee,Vahab Najari
Author-email: cranjan@processminer.com, dbanerjee@processminer.com
Classifier: Programming Language :: Python :: 3.6
Classifier: License :: OSI Approved :: MIT License
Classifier: Operating System :: OS Independent
Requires-Python: >=3.6
License-File: LICENSE
Requires-Dist: numpy
Requires-Dist: pandas
Requires-Dist: scipy
